{
  "store_key": "ueno_honkan_espass_sbj",
  "unit_id": "3126",
  "machine_key": "sbj",
  "days": [
    {
      "date": "2026-02-05",
      "art": 8,
      "rb": 2,
      "games": 781,
      "prob": 97.6,
      "is_good": true,
      "history": [
        {
          "hit_num": 1,
          "time": "12:04",
          "start": 10,
          "medals": 39,
          "type": "ART"
        },
        {
          "hit_num": 2,
          "time": "12:00",
          "start": 21,
          "medals": 222,
          "type": "ART"
        },
        {
          "hit_num": 3,
          "time": "11:54",
          "start": 2,
          "medals": 281,
          "type": "ART"
        },
        {
          "hit_num": 4,
          "time": "11:52",
          "start": 2,
          "medals": 37,
          "type": "ART"
        },
        {
          "hit_num": 5,
          "time": "11:49",
          "start": 1,
          "medals": 150,
          "type": "ART"
        },
        {
          "hit_num": 6,
          "time": "11:45",
          "start": 1,
          "medals": 28,
          "type": "ART"
        },
        {
          "hit_num": 7,
          "time": "11:40",
          "start": 19,
          "medals": 284,
          "type": "ART"
        },
        {
          "hit_num": 8,
          "time": "11:37",
          "start": 29,
          "medals": 90,
          "type": "ART"
        },
        {
          "hit_num": 9,
          "time": "11:34",
          "start": 208,
          "medals": 51,
          "type": "RB"
        },
        {
          "hit_num": 10,
          "time": "10:58",
          "start": 456,
          "medals": 51,
          "type": "RB"
        }
      ],
      "max_rensa": 8,
      "max_medals": 1131,
      "diff_medals": 452
    },
    {
      "date": "2026-02-06",
      "art": 8,
      "rb": 2,
      "games": 781,
      "prob": 97.6,
      "is_good": true,
      "history": [
        {
          "hit_num": 1,
          "time": "12:04",
          "start": 10,
          "medals": 39,
          "type": "ART"
        },
        {
          "hit_num": 2,
          "time": "12:00",
          "start": 21,
          "medals": 222,
          "type": "ART"
        },
        {
          "hit_num": 3,
          "time": "11:54",
          "start": 2,
          "medals": 281,
          "type": "ART"
        },
        {
          "hit_num": 4,
          "time": "11:52",
          "start": 2,
          "medals": 37,
          "type": "ART"
        },
        {
          "hit_num": 5,
          "time": "11:49",
          "start": 1,
          "medals": 150,
          "type": "ART"
        },
        {
          "hit_num": 6,
          "time": "11:45",
          "start": 1,
          "medals": 28,
          "type": "ART"
        },
        {
          "hit_num": 7,
          "time": "11:40",
          "start": 19,
          "medals": 284,
          "type": "ART"
        },
        {
          "hit_num": 8,
          "time": "11:37",
          "start": 29,
          "medals": 90,
          "type": "ART"
        },
        {
          "hit_num": 9,
          "time": "11:34",
          "start": 208,
          "medals": 51,
          "type": "RB"
        },
        {
          "hit_num": 10,
          "time": "10:58",
          "start": 456,
          "medals": 51,
          "type": "RB"
        }
      ],
      "max_rensa": 8,
      "max_medals": 1131,
      "diff_medals": 452
    },
    {
      "date": "2026-02-07",
      "art": 8,
      "rb": 2,
      "games": 781,
      "prob": 97.6,
      "is_good": true,
      "history": [
        {
          "hit_num": 1,
          "time": "12:04",
          "start": 10,
          "medals": 39,
          "type": "ART"
        },
        {
          "hit_num": 2,
          "time": "12:00",
          "start": 21,
          "medals": 222,
          "type": "ART"
        },
        {
          "hit_num": 3,
          "time": "11:54",
          "start": 2,
          "medals": 281,
          "type": "ART"
        },
        {
          "hit_num": 4,
          "time": "11:52",
          "start": 2,
          "medals": 37,
          "type": "ART"
        },
        {
          "hit_num": 5,
          "time": "11:49",
          "start": 1,
          "medals": 150,
          "type": "ART"
        },
        {
          "hit_num": 6,
          "time": "11:45",
          "start": 1,
          "medals": 28,
          "type": "ART"
        },
        {
          "hit_num": 7,
          "time": "11:40",
          "start": 19,
          "medals": 284,
          "type": "ART"
        },
        {
          "hit_num": 8,
          "time": "11:37",
          "start": 29,
          "medals": 90,
          "type": "ART"
        },
        {
          "hit_num": 9,
          "time": "11:34",
          "start": 208,
          "medals": 51,
          "type": "RB"
        },
        {
          "hit_num": 10,
          "time": "10:58",
          "start": 456,
          "medals": 51,
          "type": "RB"
        }
      ],
      "max_rensa": 8,
      "max_medals": 1131,
      "diff_medals": 452
    }
  ],
  "last_updated": "2026-02-07T10:11:54.277041"
}