{"store_key": "akihabara_espass_hokuto", "unit_id": "2068", "days": [{"date": "2026-01-27", "art": 50, "rb": 13, "total_start": 3570, "history": [{"hit_num": 1, "time": "17:39", "start": 0, "medals": 152, "type": "ART"}, {"hit_num": 2, "time": "17:37", "start": 0, "medals": 181, "type": "ART"}, {"hit_num": 3, "time": "17:34", "start": 0, "medals": 111, "type": "ART"}, {"hit_num": 4, "time": "17:32", "start": 1, "medals": 163, "type": "ART"}, {"hit_num": 5, "time": "17:32", "start": 376, "medals": 10, "type": "RB"}, {"hit_num": 6, "time": "17:03", "start": 0, "medals": 168, "type": "ART"}, {"hit_num": 7, "time": "17:00", "start": 0, "medals": 155, "type": "ART"}, {"hit_num": 8, "time": "16:58", "start": 0, "medals": 122, "type": "ART"}, {"hit_num": 9, "time": "16:56", "start": 0, "medals": 79, "type": "ART"}, {"hit_num": 10, "time": "16:53", "start": 0, "medals": 190, "type": "ART"}, {"hit_num": 11, "time": "16:51", "start": 0, "medals": 112, "type": "ART"}, {"hit_num": 12, "time": "16:48", "start": 0, "medals": 198, "type": "ART"}, {"hit_num": 13, "time": "16:45", "start": 1, "medals": 129, "type": "ART"}, {"hit_num": 14, "time": "16:45", "start": 200, "medals": 10, "type": "RB"}, {"hit_num": 15, "time": "16:29", "start": 0, "medals": 153, "type": "ART"}, {"hit_num": 16, "time": "16:26", "start": 0, "medals": 177, "type": "ART"}, {"hit_num": 17, "time": "16:24", "start": 0, "medals": 176, "type": "ART"}, {"hit_num": 18, "time": "16:21", "start": 0, "medals": 122, "type": "ART"}, {"hit_num": 19, "time": "16:19", "start": 0, "medals": 127, "type": "ART"}, {"hit_num": 20, "time": "16:16", "start": 0, "medals": 137, "type": "ART"}, {"hit_num": 21, "time": "16:13", "start": 1, "medals": 149, "type": "ART"}, {"hit_num": 22, "time": "16:13", "start": 283, "medals": 10, "type": "RB"}, {"hit_num": 23, "time": "15:51", "start": 0, "medals": 139, "type": "ART"}, {"hit_num": 24, "time": "15:49", "start": 1, "medals": 102, "type": "ART"}, {"hit_num": 25, "time": "15:49", "start": 130, "medals": 10, "type": "RB"}, {"hit_num": 26, "time": "15:29", "start": 0, "medals": 144, "type": "ART"}, {"hit_num": 27, "time": "15:25", "start": 0, "medals": 133, "type": "ART"}, {"hit_num": 28, "time": "15:22", "start": 0, "medals": 178, "type": "ART"}, {"hit_num": 29, "time": "15:20", "start": 0, "medals": 131, "type": "ART"}, {"hit_num": 30, "time": "15:17", "start": 0, "medals": 125, "type": "ART"}, {"hit_num": 31, "time": "15:15", "start": 1, "medals": 130, "type": "ART"}, {"hit_num": 32, "time": "15:15", "start": 87, "medals": 10, "type": "RB"}, {"hit_num": 33, "time": "15:06", "start": 0, "medals": 146, "type": "ART"}, {"hit_num": 34, "time": "15:03", "start": 0, "medals": 170, "type": "ART"}, {"hit_num": 35, "time": "15:00", "start": 0, "medals": 108, "type": "ART"}, {"hit_num": 36, "time": "14:58", "start": 0, "medals": 119, "type": "ART"}, {"hit_num": 37, "time": "14:53", "start": 0, "medals": 159, "type": "ART"}, {"hit_num": 38, "time": "14:51", "start": 0, "medals": 149, "type": "ART"}, {"hit_num": 39, "time": "14:51", "start": 135, "medals": 3, "type": "RB"}, {"hit_num": 40, "time": "14:38", "start": 0, "medals": 184, "type": "ART"}, {"hit_num": 41, "time": "14:38", "start": 381, "medals": 2, "type": "RB"}, {"hit_num": 42, "time": "13:27", "start": 0, "medals": 131, "type": "ART"}, {"hit_num": 43, "time": "13:25", "start": 0, "medals": 143, "type": "ART"}, {"hit_num": 44, "time": "13:25", "start": 572, "medals": 2, "type": "RB"}, {"hit_num": 45, "time": "12:38", "start": 0, "medals": 129, "type": "ART"}, {"hit_num": 46, "time": "12:35", "start": 0, "medals": 159, "type": "ART"}, {"hit_num": 47, "time": "12:32", "start": 0, "medals": 139, "type": "ART"}, {"hit_num": 48, "time": "12:32", "start": 171, "medals": 10, "type": "RB"}, {"hit_num": 49, "time": "12:16", "start": 0, "medals": 134, "type": "ART"}, {"hit_num": 50, "time": "12:13", "start": 0, "medals": 136, "type": "ART"}, {"hit_num": 51, "time": "12:10", "start": 0, "medals": 113, "type": "ART"}, {"hit_num": 52, "time": "12:10", "start": 876, "medals": 10, "type": "RB"}, {"hit_num": 53, "time": "10:57", "start": 0, "medals": 152, "type": "ART"}, {"hit_num": 54, "time": "10:54", "start": 0, "medals": 143, "type": "ART"}, {"hit_num": 55, "time": "10:51", "start": 0, "medals": 117, "type": "ART"}, {"hit_num": 56, "time": "10:48", "start": 0, "medals": 105, "type": "ART"}, {"hit_num": 57, "time": "10:48", "start": 29, "medals": 3, "type": "RB"}, {"hit_num": 58, "time": "10:41", "start": 0, "medals": 182, "type": "ART"}, {"hit_num": 59, "time": "10:39", "start": 0, "medals": 132, "type": "ART"}, {"hit_num": 60, "time": "10:35", "start": 1, "medals": 95, "type": "ART"}, {"hit_num": 61, "time": "10:35", "start": 156, "medals": 10, "type": "RB"}, {"hit_num": 62, "time": "10:19", "start": 1, "medals": 135, "type": "ART"}, {"hit_num": 63, "time": "10:19", "start": 167, "medals": 10, "type": "RB"}]}, {"date": "2026-01-28", "art": 50, "rb": 13, "total_start": 3570, "history": [{"hit_num": 1, "time": "17:39", "start": 0, "medals": 152, "type": "ART"}, {"hit_num": 2, "time": "17:37", "start": 0, "medals": 181, "type": "ART"}, {"hit_num": 3, "time": "17:34", "start": 0, "medals": 111, "type": "ART"}, {"hit_num": 4, "time": "17:32", "start": 1, "medals": 163, "type": "ART"}, {"hit_num": 5, "time": "17:32", "start": 376, "medals": 10, "type": "RB"}, {"hit_num": 6, "time": "17:03", "start": 0, "medals": 168, "type": "ART"}, {"hit_num": 7, "time": "17:00", "start": 0, "medals": 155, "type": "ART"}, {"hit_num": 8, "time": "16:58", "start": 0, "medals": 122, "type": "ART"}, {"hit_num": 9, "time": "16:56", "start": 0, "medals": 79, "type": "ART"}, {"hit_num": 10, "time": "16:53", "start": 0, "medals": 190, "type": "ART"}, {"hit_num": 11, "time": "16:51", "start": 0, "medals": 112, "type": "ART"}, {"hit_num": 12, "time": "16:48", "start": 0, "medals": 198, "type": "ART"}, {"hit_num": 13, "time": "16:45", "start": 1, "medals": 129, "type": "ART"}, {"hit_num": 14, "time": "16:45", "start": 200, "medals": 10, "type": "RB"}, {"hit_num": 15, "time": "16:29", "start": 0, "medals": 153, "type": "ART"}, {"hit_num": 16, "time": "16:26", "start": 0, "medals": 177, "type": "ART"}, {"hit_num": 17, "time": "16:24", "start": 0, "medals": 176, "type": "ART"}, {"hit_num": 18, "time": "16:21", "start": 0, "medals": 122, "type": "ART"}, {"hit_num": 19, "time": "16:19", "start": 0, "medals": 127, "type": "ART"}, {"hit_num": 20, "time": "16:16", "start": 0, "medals": 137, "type": "ART"}, {"hit_num": 21, "time": "16:13", "start": 1, "medals": 149, "type": "ART"}, {"hit_num": 22, "time": "16:13", "start": 283, "medals": 10, "type": "RB"}, {"hit_num": 23, "time": "15:51", "start": 0, "medals": 139, "type": "ART"}, {"hit_num": 24, "time": "15:49", "start": 1, "medals": 102, "type": "ART"}, {"hit_num": 25, "time": "15:49", "start": 130, "medals": 10, "type": "RB"}, {"hit_num": 26, "time": "15:29", "start": 0, "medals": 144, "type": "ART"}, {"hit_num": 27, "time": "15:25", "start": 0, "medals": 133, "type": "ART"}, {"hit_num": 28, "time": "15:22", "start": 0, "medals": 178, "type": "ART"}, {"hit_num": 29, "time": "15:20", "start": 0, "medals": 131, "type": "ART"}, {"hit_num": 30, "time": "15:17", "start": 0, "medals": 125, "type": "ART"}, {"hit_num": 31, "time": "15:15", "start": 1, "medals": 130, "type": "ART"}, {"hit_num": 32, "time": "15:15", "start": 87, "medals": 10, "type": "RB"}, {"hit_num": 33, "time": "15:06", "start": 0, "medals": 146, "type": "ART"}, {"hit_num": 34, "time": "15:03", "start": 0, "medals": 170, "type": "ART"}, {"hit_num": 35, "time": "15:00", "start": 0, "medals": 108, "type": "ART"}, {"hit_num": 36, "time": "14:58", "start": 0, "medals": 119, "type": "ART"}, {"hit_num": 37, "time": "14:53", "start": 0, "medals": 159, "type": "ART"}, {"hit_num": 38, "time": "14:51", "start": 0, "medals": 149, "type": "ART"}, {"hit_num": 39, "time": "14:51", "start": 135, "medals": 3, "type": "RB"}, {"hit_num": 40, "time": "14:38", "start": 0, "medals": 184, "type": "ART"}, {"hit_num": 41, "time": "14:38", "start": 381, "medals": 2, "type": "RB"}, {"hit_num": 42, "time": "13:27", "start": 0, "medals": 131, "type": "ART"}, {"hit_num": 43, "time": "13:25", "start": 0, "medals": 143, "type": "ART"}, {"hit_num": 44, "time": "13:25", "start": 572, "medals": 2, "type": "RB"}, {"hit_num": 45, "time": "12:38", "start": 0, "medals": 129, "type": "ART"}, {"hit_num": 46, "time": "12:35", "start": 0, "medals": 159, "type": "ART"}, {"hit_num": 47, "time": "12:32", "start": 0, "medals": 139, "type": "ART"}, {"hit_num": 48, "time": "12:32", "start": 171, "medals": 10, "type": "RB"}, {"hit_num": 49, "time": "12:16", "start": 0, "medals": 134, "type": "ART"}, {"hit_num": 50, "time": "12:13", "start": 0, "medals": 136, "type": "ART"}, {"hit_num": 51, "time": "12:10", "start": 0, "medals": 113, "type": "ART"}, {"hit_num": 52, "time": "12:10", "start": 876, "medals": 10, "type": "RB"}, {"hit_num": 53, "time": "10:57", "start": 0, "medals": 152, "type": "ART"}, {"hit_num": 54, "time": "10:54", "start": 0, "medals": 143, "type": "ART"}, {"hit_num": 55, "time": "10:51", "start": 0, "medals": 117, "type": "ART"}, {"hit_num": 56, "time": "10:48", "start": 0, "medals": 105, "type": "ART"}, {"hit_num": 57, "time": "10:48", "start": 29, "medals": 3, "type": "RB"}, {"hit_num": 58, "time": "10:41", "start": 0, "medals": 182, "type": "ART"}, {"hit_num": 59, "time": "10:39", "start": 0, "medals": 132, "type": "ART"}, {"hit_num": 60, "time": "10:35", "start": 1, "medals": 95, "type": "ART"}, {"hit_num": 61, "time": "10:35", "start": 156, "medals": 10, "type": "RB"}, {"hit_num": 62, "time": "10:19", "start": 1, "medals": 135, "type": "ART"}, {"hit_num": 63, "time": "10:19", "start": 167, "medals": 10, "type": "RB"}]}]}