{
  "store_key": "island_akihabara_hokuto_tensei2",
  "unit_id": "0732",
  "machine_key": "hokuto_tensei2",
  "days": [
    {
      "date": "2026-01-27",
      "art": 57,
      "rb": 10,
      "games": 0,
      "prob": 0,
      "is_good": false
    },
    {
      "date": "2026-01-26",
      "art": 63,
      "rb": 19,
      "games": 0,
      "prob": 0,
      "is_good": false
    },
    {
      "date": "2026-01-25",
      "art": 91,
      "rb": 17,
      "games": 0,
      "prob": 0,
      "is_good": false
    },
    {
      "date": "2026-01-24",
      "art": 43,
      "rb": 15,
      "games": 0,
      "prob": 0,
      "is_good": false
    },
    {
      "date": "2026-01-23",
      "art": 37,
      "rb": 12,
      "games": 0,
      "prob": 0,
      "is_good": false
    },
    {
      "date": "2026-01-22",
      "art": 58,
      "rb": 12,
      "games": 0,
      "prob": 0,
      "is_good": false
    },
    {
      "unit_id": "0732",
      "date": "2026-01-21",
      "bb": 0,
      "rb": 14,
      "art": 44,
      "total_start": 7716,
      "final_start": 271,
      "art_games": 1525,
      "max_medals": 1063,
      "combined_prob": 551,
      "prob": 175.4,
      "is_good": true
    },
    {
      "unit_id": "0732",
      "date": "2026-01-20",
      "bb": 0,
      "rb": 14,
      "art": 43,
      "total_start": 7349,
      "final_start": 190,
      "art_games": 1526,
      "max_medals": 1545,
      "combined_prob": 525,
      "prob": 170.9,
      "is_good": true
    },
    {
      "unit_id": "0732",
      "date": "2026-01-19",
      "bb": 0,
      "rb": 12,
      "art": 72,
      "total_start": 7750,
      "final_start": 2,
      "art_games": 3148,
      "max_medals": 8422,
      "combined_prob": 646,
      "prob": 107.6,
      "is_good": true
    },
    {
      "unit_id": "0732",
      "date": "2026-01-18",
      "bb": 0,
      "rb": 13,
      "art": 34,
      "total_start": 6100,
      "final_start": 126,
      "art_games": 1202,
      "max_medals": 1441,
      "combined_prob": 469,
      "prob": 179.4,
      "is_good": true
    },
    {
      "unit_id": "0732",
      "date": "2026-01-17",
      "bb": 0,
      "rb": 15,
      "art": 70,
      "total_start": 8099,
      "final_start": 322,
      "art_games": 2265,
      "max_medals": 4745,
      "combined_prob": 540,
      "prob": 115.7,
      "is_good": true
    },
    {
      "unit_id": "0732",
      "date": "2026-01-16",
      "bb": 0,
      "rb": 14,
      "art": 31,
      "total_start": 7150,
      "final_start": 3,
      "art_games": 1048,
      "max_medals": 734,
      "combined_prob": 511,
      "prob": 230.6,
      "is_good": true
    },
    {
      "unit_id": "0732",
      "date": "2026-01-15",
      "bb": 0,
      "rb": 14,
      "art": 44,
      "total_start": 7400,
      "final_start": 156,
      "art_games": 1510,
      "max_medals": 1097,
      "combined_prob": 529,
      "prob": 168.2,
      "is_good": true
    }
  ],
  "last_updated": "2026-01-28T07:59:15.225572"
}