{
  "store_key": "island_akihabara_hokuto",
  "unit_id": "0815",
  "machine_key": "hokuto_tensei2",
  "days": [
    {
      "date": "2026-02-06",
      "art": 0,
      "rb": 0,
      "games": 0,
      "prob": null,
      "is_good": false,
      "history": [],
      "max_rensa": 0,
      "max_medals": 0,
      "diff_medals": null
    },
    {
      "date": "2026-02-07",
      "art": 0,
      "rb": 0,
      "games": 0,
      "prob": null,
      "is_good": false,
      "history": [
        {
          "hit_num": 1,
          "time": "20:04",
          "start": 0,
          "medals": 125,
          "type": "ART"
        },
        {
          "hit_num": 2,
          "time": "20:02",
          "start": 0,
          "medals": 173,
          "type": "ART"
        },
        {
          "hit_num": 3,
          "time": "19:59",
          "start": 0,
          "medals": 177,
          "type": "ART"
        },
        {
          "hit_num": 1,
          "time": "19:54",
          "start": 0,
          "medals": 0,
          "type": "ART"
        },
        {
          "hit_num": 2,
          "time": "19:51",
          "start": 0,
          "medals": 96,
          "type": "ART"
        },
        {
          "hit_num": 3,
          "time": "19:49",
          "start": 0,
          "medals": 179,
          "type": "ART"
        },
        {
          "hit_num": 4,
          "time": "19:46",
          "start": 0,
          "medals": 100,
          "type": "ART"
        },
        {
          "hit_num": 5,
          "time": "19:43",
          "start": 0,
          "medals": 152,
          "type": "ART"
        },
        {
          "hit_num": 6,
          "time": "19:41",
          "start": 1,
          "medals": 177,
          "type": "ART"
        },
        {
          "hit_num": 7,
          "time": "19:41",
          "start": 393,
          "medals": 2,
          "type": "REG"
        },
        {
          "hit_num": 1,
          "time": "19:05",
          "start": 1,
          "medals": 169,
          "type": "ART"
        },
        {
          "hit_num": 2,
          "time": "19:05",
          "start": 669,
          "medals": 10,
          "type": "REG"
        },
        {
          "hit_num": 1,
          "time": "17:13",
          "start": 0,
          "medals": 135,
          "type": "ART"
        },
        {
          "hit_num": 2,
          "time": "17:11",
          "start": 0,
          "medals": 151,
          "type": "ART"
        },
        {
          "hit_num": 3,
          "time": "17:11",
          "start": 220,
          "medals": 10,
          "type": "REG"
        },
        {
          "hit_num": 4,
          "time": "16:51",
          "start": 0,
          "medals": 183,
          "type": "ART"
        },
        {
          "hit_num": 5,
          "time": "16:47",
          "start": 0,
          "medals": 140,
          "type": "ART"
        },
        {
          "hit_num": 6,
          "time": "16:47",
          "start": 405,
          "medals": 10,
          "type": "REG"
        },
        {
          "hit_num": 1,
          "time": "14:28",
          "start": 0,
          "medals": 144,
          "type": "ART"
        },
        {
          "hit_num": 2,
          "time": "14:25",
          "start": 0,
          "medals": 127,
          "type": "ART"
        },
        {
          "hit_num": 3,
          "time": "14:25",
          "start": 342,
          "medals": 0,
          "type": "REG"
        },
        {
          "hit_num": 4,
          "time": "13:56",
          "start": 1,
          "medals": 144,
          "type": "ART"
        },
        {
          "hit_num": 5,
          "time": "13:56",
          "start": 120,
          "medals": 10,
          "type": "REG"
        },
        {
          "hit_num": 6,
          "time": "13:43",
          "start": 0,
          "medals": 136,
          "type": "ART"
        },
        {
          "hit_num": 7,
          "time": "13:43",
          "start": 829,
          "medals": 10,
          "type": "REG"
        },
        {
          "hit_num": 8,
          "time": "12:38",
          "start": 0,
          "medals": 164,
          "type": "ART"
        },
        {
          "hit_num": 9,
          "time": "12:35",
          "start": 0,
          "medals": 154,
          "type": "ART"
        },
        {
          "hit_num": 10,
          "time": "12:33",
          "start": 0,
          "medals": 111,
          "type": "ART"
        },
        {
          "hit_num": 11,
          "time": "12:32",
          "start": 4,
          "medals": 3,
          "type": "REG"
        },
        {
          "hit_num": 12,
          "time": "12:28",
          "start": 0,
          "medals": 167,
          "type": "ART"
        },
        {
          "hit_num": 13,
          "time": "12:25",
          "start": 0,
          "medals": 94,
          "type": "ART"
        },
        {
          "hit_num": 14,
          "time": "12:22",
          "start": 0,
          "medals": 171,
          "type": "ART"
        },
        {
          "hit_num": 15,
          "time": "12:20",
          "start": 0,
          "medals": 121,
          "type": "ART"
        },
        {
          "hit_num": 16,
          "time": "12:20",
          "start": 808,
          "medals": 10,
          "type": "REG"
        },
        {
          "hit_num": 17,
          "time": "11:06",
          "start": 0,
          "medals": 87,
          "type": "ART"
        },
        {
          "hit_num": 18,
          "time": "11:03",
          "start": 0,
          "medals": 127,
          "type": "ART"
        },
        {
          "hit_num": 19,
          "time": "11:01",
          "start": 0,
          "medals": 117,
          "type": "ART"
        },
        {
          "hit_num": 20,
          "time": "11:00",
          "start": 433,
          "medals": 10,
          "type": "REG"
        },
        {
          "hit_num": 21,
          "time": "10:18",
          "start": 0,
          "medals": 137,
          "type": "ART"
        },
        {
          "hit_num": 22,
          "time": "10:18",
          "start": 72,
          "medals": 10,
          "type": "REG"
        }
      ],
      "max_rensa": 8,
      "max_medals": 1002,
      "diff_medals": null
    }
  ],
  "last_updated": "2026-02-07T10:11:54.271511"
}