{
  "store_key": "shinjuku_espass_hokuto",
  "unit_id": "16",
  "machine_key": "hokuto_tensei2",
  "days": [
    {
      "date": "2026-02-04",
      "art": 39,
      "rb": 7,
      "games": 1245,
      "prob": 31.9,
      "is_good": true,
      "history": [
        {
          "hit_num": 1,
          "time": "16:07",
          "start": 0,
          "medals": 0,
          "type": "ART"
        },
        {
          "hit_num": 2,
          "time": "16:00",
          "start": 0,
          "medals": 427,
          "type": "ART"
        },
        {
          "hit_num": 3,
          "time": "15:55",
          "start": 0,
          "medals": 250,
          "type": "ART"
        },
        {
          "hit_num": 4,
          "time": "15:41",
          "start": 0,
          "medals": 208,
          "type": "ART"
        },
        {
          "hit_num": 5,
          "time": "15:38",
          "start": 0,
          "medals": 141,
          "type": "ART"
        },
        {
          "hit_num": 6,
          "time": "15:35",
          "start": 0,
          "medals": 184,
          "type": "ART"
        },
        {
          "hit_num": 7,
          "time": "15:33",
          "start": 0,
          "medals": 131,
          "type": "ART"
        },
        {
          "hit_num": 8,
          "time": "15:29",
          "start": 0,
          "medals": 230,
          "type": "ART"
        },
        {
          "hit_num": 9,
          "time": "15:24",
          "start": 0,
          "medals": 328,
          "type": "ART"
        },
        {
          "hit_num": 10,
          "time": "15:18",
          "start": 6,
          "medals": 297,
          "type": "ART"
        },
        {
          "hit_num": 11,
          "time": "15:13",
          "start": 0,
          "medals": 264,
          "type": "ART"
        },
        {
          "hit_num": 12,
          "time": "15:11",
          "start": 0,
          "medals": 176,
          "type": "ART"
        },
        {
          "hit_num": 13,
          "time": "15:08",
          "start": 0,
          "medals": 188,
          "type": "ART"
        },
        {
          "hit_num": 14,
          "time": "15:06",
          "start": 0,
          "medals": 167,
          "type": "ART"
        },
        {
          "hit_num": 15,
          "time": "14:59",
          "start": 0,
          "medals": 259,
          "type": "ART"
        },
        {
          "hit_num": 16,
          "time": "14:56",
          "start": 0,
          "medals": 153,
          "type": "ART"
        },
        {
          "hit_num": 17,
          "time": "14:54",
          "start": 1,
          "medals": 124,
          "type": "ART"
        },
        {
          "hit_num": 18,
          "time": "14:54",
          "start": 247,
          "medals": 3,
          "type": "RB"
        },
        {
          "hit_num": 19,
          "time": "14:34",
          "start": 0,
          "medals": 131,
          "type": "ART"
        },
        {
          "hit_num": 20,
          "time": "14:32",
          "start": 1,
          "medals": 162,
          "type": "ART"
        },
        {
          "hit_num": 21,
          "time": "14:32",
          "start": 63,
          "medals": 10,
          "type": "RB"
        },
        {
          "hit_num": 22,
          "time": "14:25",
          "start": 0,
          "medals": 132,
          "type": "ART"
        },
        {
          "hit_num": 23,
          "time": "14:23",
          "start": 0,
          "medals": 116,
          "type": "ART"
        },
        {
          "hit_num": 24,
          "time": "14:20",
          "start": 0,
          "medals": 140,
          "type": "ART"
        },
        {
          "hit_num": 25,
          "time": "14:18",
          "start": 1,
          "medals": 156,
          "type": "ART"
        },
        {
          "hit_num": 26,
          "time": "14:18",
          "start": 62,
          "medals": 2,
          "type": "RB"
        },
        {
          "hit_num": 27,
          "time": "14:11",
          "start": 1,
          "medals": 129,
          "type": "ART"
        },
        {
          "hit_num": 28,
          "time": "14:11",
          "start": 20,
          "medals": 3,
          "type": "RB"
        },
        {
          "hit_num": 29,
          "time": "14:07",
          "start": 0,
          "medals": 163,
          "type": "ART"
        },
        {
          "hit_num": 30,
          "time": "14:04",
          "start": 0,
          "medals": 137,
          "type": "ART"
        },
        {
          "hit_num": 31,
          "time": "14:02",
          "start": 0,
          "medals": 140,
          "type": "ART"
        },
        {
          "hit_num": 32,
          "time": "13:59",
          "start": 0,
          "medals": 159,
          "type": "ART"
        },
        {
          "hit_num": 33,
          "time": "13:57",
          "start": 0,
          "medals": 135,
          "type": "ART"
        },
        {
          "hit_num": 34,
          "time": "13:54",
          "start": 0,
          "medals": 115,
          "type": "ART"
        },
        {
          "hit_num": 35,
          "time": "13:52",
          "start": 0,
          "medals": 124,
          "type": "ART"
        },
        {
          "hit_num": 36,
          "time": "13:50",
          "start": 0,
          "medals": 110,
          "type": "ART"
        },
        {
          "hit_num": 37,
          "time": "13:47",
          "start": 0,
          "medals": 177,
          "type": "ART"
        },
        {
          "hit_num": 38,
          "time": "13:44",
          "start": 1,
          "medals": 111,
          "type": "ART"
        },
        {
          "hit_num": 39,
          "time": "13:44",
          "start": 147,
          "medals": 2,
          "type": "RB"
        },
        {
          "hit_num": 40,
          "time": "13:31",
          "start": 0,
          "medals": 123,
          "type": "ART"
        },
        {
          "hit_num": 41,
          "time": "13:31",
          "start": 551,
          "medals": 2,
          "type": "RB"
        },
        {
          "hit_num": 42,
          "time": "11:51",
          "start": 0,
          "medals": 151,
          "type": "ART"
        },
        {
          "hit_num": 43,
          "time": "11:49",
          "start": 0,
          "medals": 111,
          "type": "ART"
        },
        {
          "hit_num": 44,
          "time": "11:46",
          "start": 0,
          "medals": 124,
          "type": "ART"
        },
        {
          "hit_num": 45,
          "time": "11:42",
          "start": 0,
          "medals": 157,
          "type": "ART"
        },
        {
          "hit_num": 46,
          "time": "11:42",
          "start": 138,
          "medals": 0,
          "type": "RB"
        }
      ],
      "max_rensa": 17,
      "max_medals": 3403,
      "diff_medals": 4585
    }
  ],
  "last_updated": "2026-02-04T18:09:30.453690"
}