{
  "store_key": "shibuya_honkan_espass_hokuto",
  "unit_id": "2036",
  "machine_key": "hokuto_tensei2",
  "days": [
    {
      "date": "2026-02-06",
      "art": 10,
      "rb": 3,
      "games": 2061,
      "prob": 206.1,
      "is_good": false,
      "history": [],
      "max_rensa": 0,
      "max_medals": 789,
      "diff_medals": null
    },
    {
      "date": "2026-02-07",
      "art": 19,
      "rb": 6,
      "games": 2214,
      "prob": 116.5,
      "is_good": true,
      "history": [
        {
          "hit_num": 1,
          "time": "19:24",
          "start": 1,
          "medals": 166,
          "type": "ART"
        },
        {
          "hit_num": 2,
          "time": "19:22",
          "start": 1,
          "medals": 141,
          "type": "ART"
        },
        {
          "hit_num": 3,
          "time": "19:18",
          "start": 1,
          "medals": 145,
          "type": "ART"
        },
        {
          "hit_num": 4,
          "time": "19:15",
          "start": 1,
          "medals": 227,
          "type": "ART"
        },
        {
          "hit_num": 5,
          "time": "19:15",
          "start": 617,
          "medals": 10,
          "type": "RB"
        },
        {
          "hit_num": 1,
          "time": "18:30",
          "start": 1,
          "medals": 127,
          "type": "ART"
        },
        {
          "hit_num": 2,
          "time": "18:28",
          "start": 1,
          "medals": 147,
          "type": "ART"
        },
        {
          "hit_num": 3,
          "time": "18:27",
          "start": 209,
          "medals": 10,
          "type": "RB"
        },
        {
          "hit_num": 4,
          "time": "18:10",
          "start": 0,
          "medals": 148,
          "type": "ART"
        },
        {
          "hit_num": 1,
          "time": "18:08",
          "start": 1,
          "medals": 0,
          "type": "ART"
        },
        {
          "hit_num": 2,
          "time": "18:05",
          "start": 0,
          "medals": 164,
          "type": "ART"
        },
        {
          "hit_num": 3,
          "time": "18:03",
          "start": 0,
          "medals": 120,
          "type": "ART"
        },
        {
          "hit_num": 4,
          "time": "18:00",
          "start": 0,
          "medals": 120,
          "type": "ART"
        },
        {
          "hit_num": 5,
          "time": "17:56",
          "start": 1,
          "medals": 226,
          "type": "ART"
        },
        {
          "hit_num": 6,
          "time": "17:54",
          "start": 1,
          "medals": 70,
          "type": "ART"
        },
        {
          "hit_num": 7,
          "time": "17:52",
          "start": 1,
          "medals": 93,
          "type": "ART"
        },
        {
          "hit_num": 8,
          "time": "17:52",
          "start": 371,
          "medals": 2,
          "type": "RB"
        },
        {
          "hit_num": 1,
          "time": "17:24",
          "start": 1,
          "medals": 152,
          "type": "ART"
        },
        {
          "hit_num": 2,
          "time": "17:21",
          "start": 0,
          "medals": 138,
          "type": "ART"
        },
        {
          "hit_num": 3,
          "time": "17:21",
          "start": 510,
          "medals": 10,
          "type": "RB"
        },
        {
          "hit_num": 1,
          "time": "15:02",
          "start": 1,
          "medals": 140,
          "type": "ART"
        },
        {
          "hit_num": 2,
          "time": "15:00",
          "start": 0,
          "medals": 129,
          "type": "ART"
        },
        {
          "hit_num": 3,
          "time": "14:59",
          "start": 103,
          "medals": 10,
          "type": "RB"
        },
        {
          "hit_num": 4,
          "time": "14:49",
          "start": 0,
          "medals": 153,
          "type": "ART"
        },
        {
          "hit_num": 5,
          "time": "14:49",
          "start": 161,
          "medals": 10,
          "type": "RB"
        }
      ],
      "max_rensa": 7,
      "max_medals": 848,
      "diff_medals": -840
    }
  ],
  "last_updated": "2026-02-07T10:11:54.183086"
}